{"channels":[{"iso":"BE","name":"Kortrijk › West: Grote Markt Kortrijk","description":"Kortrijk, Flanders","logo":"https://imgproxy.windy.com/_/icon/plain/current/1182187060/original.jpg","type":"webcam","url":"https://webcams.windy.com/webcams/public/embed/player/1182187060/day","source":"https://www.windy.com","source_name":"Windy"},{"iso":"BE","name":"De Panne: Sea promenade beach strand","description":"De Panne, Flanders","logo":"https://imgproxy.windy.com/_/icon/plain/current/1183494194/original.jpg","type":"webcam","url":"https://webcams.windy.com/webcams/public/embed/player/1183494194/live","source":"https://www.windy.com","source_name":"Windy"},{"iso":"BE","name":"Enghien: REBECQ BELGIQUE","description":"Enghien, Wallonia","logo":"https://imgproxy.windy.com/_/icon/plain/current/1187876054/original.jpg","type":"webcam","url":"https://webcams.windy.com/webcams/public/embed/player/1187876054/day","source":"https://www.windy.com","source_name":"Windy"},{"iso":"BE","name":"Cerfontaine: Station météo de - Lacs de l'Eau d' Heure, Belgique","description":"Cerfontaine, Wallonia","logo":"https://imgproxy.windy.com/_/icon/plain/current/1196859128/original.jpg","type":"webcam","url":"https://webcams.windy.com/webcams/public/embed/player/1196859128/day","source":"https://www.windy.com","source_name":"Windy"},{"iso":"BE","name":"Kampenhout","description":"Kampenhout, Flanders","logo":"https://imgproxy.windy.com/_/icon/plain/current/1215958700/original.jpg","type":"webcam","url":"https://webcams.windy.com/webcams/public/embed/player/1215958700/day","source":"https://www.windy.com","source_name":"Windy"},{"iso":"BE","name":"Zeebrugge: Zeedijk","description":"Zeebrugge, Flanders","logo":"https://imgproxy.windy.com/_/icon/plain/current/1232545015/original.jpg","type":"webcam","url":"https://webcams.windy.com/webcams/public/embed/player/1232545015/live","source":"https://www.windy.com","source_name":"Windy"},{"iso":"BE","name":"Kalmthout: Ransberg","description":"Kalmthout, Flanders","logo":"https://imgproxy.windy.com/_/icon/plain/current/1247136712/original.jpg","type":"webcam","url":"https://webcams.windy.com/webcams/public/embed/player/1247136712/day","source":"https://www.windy.com","source_name":"Windy"},{"iso":"BE","name":"Ghent: UGent Volkssterrenwacht","description":"Ghent, Flanders","logo":"https://imgproxy.windy.com/_/icon/plain/current/1296555442/original.jpg","type":"webcam","url":"https://webcams.windy.com/webcams/public/embed/player/1296555442/day","source":"https://www.windy.com","source_name":"Windy"},{"iso":"BE","name":"Antwerp › North: Zicht op de schelde","description":"Antwerp, Flanders","logo":"https://imgproxy.windy.com/_/icon/plain/current/1296578281/original.jpg","type":"webcam","url":"https://webcams.windy.com/webcams/public/embed/player/1296578281/day","source":"https://www.windy.com","source_name":"Windy"},{"iso":"BE","name":"Ottignies-Louvain-la-Neuve: Ottignies: L.N.N. Météo ON4MBL - WebCam en Live","description":"Ottignies-Louvain-la-Neuve, Wallonia","logo":"https://imgproxy.windy.com/_/icon/plain/current/1317633173/original.jpg","type":"webcam","url":"https://webcams.windy.com/webcams/public/embed/player/1317633173/day","source":"https://www.windy.com","source_name":"Windy"},{"iso":"BE","name":"Godarville › South-west: Météo","description":"Godarville, Wallonia","logo":"https://imgproxy.windy.com/_/icon/plain/current/1327185362/original.jpg","type":"webcam","url":"https://webcams.windy.com/webcams/public/embed/player/1327185362/day","source":"https://www.windy.com","source_name":"Windy"},{"iso":"BE","name":"Lubbeek: Craywinckelhof","description":"Lubbeek, Flanders","logo":"https://imgproxy.windy.com/_/icon/plain/current/1342223159/original.jpg","type":"webcam","url":"https://webcams.windy.com/webcams/public/embed/player/1342223159/live","source":"https://www.windy.com","source_name":"Windy"},{"iso":"BE","name":"Bullingen › North: Flugplatz","description":"Bullingen, Wallonia","logo":"https://imgproxy.windy.com/_/icon/plain/current/1349694601/original.jpg","type":"webcam","url":"https://webcams.windy.com/webcams/public/embed/player/1349694601/day","source":"https://www.windy.com","source_name":"Windy"},{"iso":"BE","name":"Poperinge: Grote Markt","description":"Poperinge, Flanders","logo":"https://imgproxy.windy.com/_/icon/plain/current/1354824758/original.jpg","type":"webcam","url":"https://webcams.windy.com/webcams/public/embed/player/1354824758/day","source":"https://www.windy.com","source_name":"Windy"},{"iso":"BE","name":"Montbliart: Sivry-Rance","description":"Montbliart, Wallonia","logo":"https://imgproxy.windy.com/_/icon/plain/current/1367662116/original.jpg","type":"webcam","url":"https://webcams.windy.com/webcams/public/embed/player/1367662116/day","source":"https://www.windy.com","source_name":"Windy"},{"iso":"BE","name":"Jodoigne: Bvd des Rendanges","description":"Jodoigne, Wallonia","logo":"https://imgproxy.windy.com/_/icon/plain/current/1367668006/original.jpg","type":"webcam","url":"https://webcams.windy.com/webcams/public/embed/player/1367668006/day","source":"https://www.windy.com","source_name":"Windy"},{"iso":"BE","name":"Bilzen › North-west: Diepenbeek (B) - Weather Station","description":"Bilzen, Flanders","logo":"https://imgproxy.windy.com/_/icon/plain/current/1377676358/original.jpg","type":"webcam","url":"https://webcams.windy.com/webcams/public/embed/player/1377676358/day","source":"https://www.windy.com","source_name":"Windy"},{"iso":"BE","name":"Goe: Wesertalwetter","description":"Goe, Wallonia","logo":"https://imgproxy.windy.com/_/icon/plain/current/1391950651/original.jpg","type":"webcam","url":"https://webcams.windy.com/webcams/public/embed/player/1391950651/day","source":"https://www.windy.com","source_name":"Windy"},{"iso":"BE","name":"Lobbes: Meteo","description":"Lobbes, Wallonia","logo":"https://imgproxy.windy.com/_/icon/plain/current/1394391845/original.jpg","type":"webcam","url":"https://webcams.windy.com/webcams/public/embed/player/1394391845/day","source":"https://www.windy.com","source_name":"Windy"},{"iso":"BE","name":"Zonhoven: De Wijers","description":"Zonhoven, Flanders","logo":"https://imgproxy.windy.com/_/icon/plain/current/1395445586/original.jpg","type":"webcam","url":"https://webcams.windy.com/webcams/public/embed/player/1395445586/live","source":"https://www.windy.com","source_name":"Windy"},{"iso":"BE","name":"Leglise: Witry › South-west: La Moyemont","description":"Leglise, Wallonia","logo":"https://imgproxy.windy.com/_/icon/plain/current/1397508900/original.jpg","type":"webcam","url":"https://webcams.windy.com/webcams/public/embed/player/1397508900/day","source":"https://www.windy.com","source_name":"Windy"},{"iso":"BE","name":"Bougnies: Quevy","description":"Bougnies, Wallonia","logo":"https://imgproxy.windy.com/_/icon/plain/current/1408354475/original.jpg","type":"webcam","url":"https://webcams.windy.com/webcams/public/embed/player/1408354475/day","source":"https://www.windy.com","source_name":"Windy"},{"iso":"BE","name":"Waimes: Botrange - Walloon, Belgium","description":"Waimes, Wallonia","logo":"https://imgproxy.windy.com/_/icon/plain/current/1419604218/original.jpg","type":"webcam","url":"https://webcams.windy.com/webcams/public/embed/player/1419604218/day","source":"https://www.windy.com","source_name":"Windy"},{"iso":"BE","name":"Melin › South-west: Wallonia, Belgium","description":"Melin, Wallonia","logo":"https://imgproxy.windy.com/_/icon/plain/current/1451952327/original.jpg","type":"webcam","url":"https://webcams.windy.com/webcams/public/embed/player/1451952327/day","source":"https://www.windy.com","source_name":"Windy"},{"iso":"BE","name":"De Panne › North-west: beach, Belgium: Beach","description":"De Panne, Flanders","logo":"https://imgproxy.windy.com/_/icon/plain/current/1454667016/original.jpg","type":"webcam","url":"https://webcams.windy.com/webcams/public/embed/player/1454667016/day","source":"https://www.windy.com","source_name":"Windy"},{"iso":"BE","name":"Westende-Bad: Westende","description":"Westende-Bad, Flanders","logo":"https://imgproxy.windy.com/_/icon/plain/current/1461870219/original.jpg","type":"webcam","url":"https://webcams.windy.com/webcams/public/embed/player/1461870219/live","source":"https://www.windy.com","source_name":"Windy"},{"iso":"BE","name":"Genappe › South-west: EBBY: EBBY AÉRODROME","description":"Genappe, Wallonia","logo":"https://imgproxy.windy.com/_/icon/plain/current/1480157587/original.jpg","type":"webcam","url":"https://webcams.windy.com/webcams/public/embed/player/1480157587/day","source":"https://www.windy.com","source_name":"Windy"},{"iso":"BE","name":"Enghien › North-east: Ciel! Belgique","description":"Enghien, Wallonia","logo":"https://imgproxy.windy.com/_/icon/plain/current/1487025435/original.jpg","type":"webcam","url":"https://webcams.windy.com/webcams/public/embed/player/1487025435/day","source":"https://www.windy.com","source_name":"Windy"},{"iso":"BE","name":"Kortenaken › South-east: Hoeleden - Flanders, Belgium","description":"Kortenaken, Flanders","logo":"https://imgproxy.windy.com/_/icon/plain/current/1496382166/original.jpg","type":"webcam","url":"https://webcams.windy.com/webcams/public/embed/player/1496382166/day","source":"https://www.windy.com","source_name":"Windy"},{"iso":"BE","name":"Grimbergen › South-west: Grimbergen Airfield","description":"Grimbergen, Flanders","logo":"https://imgproxy.windy.com/_/icon/plain/current/1503755698/original.jpg","type":"webcam","url":"https://webcams.windy.com/webcams/public/embed/player/1503755698/day","source":"https://www.windy.com","source_name":"Windy"},{"iso":"BE","name":"Zonhoven › West: Flanders, Belgium","description":"Zonhoven, Flanders","logo":"https://imgproxy.windy.com/_/icon/plain/current/1528013469/original.jpg","type":"webcam","url":"https://webcams.windy.com/webcams/public/embed/player/1528013469/day","source":"https://www.windy.com","source_name":"Windy"},{"iso":"BE","name":"Genk › North-east: Zwartberg Airfield","description":"Genk, Flanders","logo":"https://imgproxy.windy.com/_/icon/plain/current/1532853294/original.jpg","type":"webcam","url":"https://webcams.windy.com/webcams/public/embed/player/1532853294/day","source":"https://www.windy.com","source_name":"Windy"},{"iso":"BE","name":"Balen: Keiheuvel - Flanders, Belgium","description":"Balen, Flanders","logo":"https://imgproxy.windy.com/_/icon/plain/current/1544888167/original.jpg","type":"webcam","url":"https://webcams.windy.com/webcams/public/embed/player/1544888167/day","source":"https://www.windy.com","source_name":"Windy"},{"iso":"BE","name":"Hannut: Avernas-le-Bauduin - Wallonia, Belgium","description":"Hannut, Wallonia","logo":"https://imgproxy.windy.com/_/icon/plain/current/1560336232/original.jpg","type":"webcam","url":"https://webcams.windy.com/webcams/public/embed/player/1560336232/day","source":"https://www.windy.com","source_name":"Windy"},{"iso":"BE","name":"Rochehaut › South: Frahan","description":"Rochehaut, Wallonia","logo":"https://imgproxy.windy.com/_/icon/plain/current/1562831720/original.jpg","type":"webcam","url":"https://webcams.windy.com/webcams/public/embed/player/1562831720/day","source":"https://www.windy.com","source_name":"Windy"},{"iso":"BE","name":"Braine-l’Alleud › South: Braine","description":"Braine-l’Alleud, Wallonia","logo":"https://imgproxy.windy.com/_/icon/plain/current/1564569382/original.jpg","type":"webcam","url":"https://webcams.windy.com/webcams/public/embed/player/1564569382/day","source":"https://www.windy.com","source_name":"Windy"},{"iso":"BE","name":"Sterpenich: Arlon/Sterpenich Airport","description":"Sterpenich, Wallonia","logo":"https://imgproxy.windy.com/_/icon/plain/current/1565975114/original.jpg","type":"webcam","url":"https://webcams.windy.com/webcams/public/embed/player/1565975114/day","source":"https://www.windy.com","source_name":"Windy"},{"iso":"BE","name":"Pin › North: Wallonia, Belgium","description":"Pin, Wallonia","logo":"https://imgproxy.windy.com/_/icon/plain/current/1566888489/original.jpg","type":"webcam","url":"https://webcams.windy.com/webcams/public/embed/player/1566888489/day","source":"https://www.windy.com","source_name":"Windy"},{"iso":"BE","name":"Andenne › North-west: Andenelle - Wallonia, Belgium","description":"Andenne, Wallonia","logo":"https://imgproxy.windy.com/_/icon/plain/current/1566888834/original.jpg","type":"webcam","url":"https://webcams.windy.com/webcams/public/embed/player/1566888834/day","source":"https://www.windy.com","source_name":"Windy"},{"iso":"BE","name":"Verviers: Wallonia, Belgium","description":"Verviers, Wallonia","logo":"https://imgproxy.windy.com/_/icon/plain/current/1572626413/original.jpg","type":"webcam","url":"https://webcams.windy.com/webcams/public/embed/player/1572626413/day","source":"https://www.windy.com","source_name":"Windy"},{"iso":"BE","name":"Malmedy › South-east: Xhoffraix","description":"Malmedy, Wallonia","logo":"https://imgproxy.windy.com/_/icon/plain/current/1577992890/original.jpg","type":"webcam","url":"https://webcams.windy.com/webcams/public/embed/player/1577992890/day","source":"https://www.windy.com","source_name":"Windy"},{"iso":"BE","name":"Assesse","description":"Assesse, Wallonia","logo":"https://imgproxy.windy.com/_/icon/plain/current/1578743945/original.jpg","type":"webcam","url":"https://webcams.windy.com/webcams/public/embed/player/1578743945/day","source":"https://www.windy.com","source_name":"Windy"},{"iso":"BE","name":"Waimes: High Fens","description":"Waimes, Wallonia","logo":"https://imgproxy.windy.com/_/icon/plain/current/1581361459/original.jpg","type":"webcam","url":"https://webcams.windy.com/webcams/public/embed/player/1581361459/day","source":"https://www.windy.com","source_name":"Windy"},{"iso":"BE","name":"Bruges: Zeebrugge","description":"Bruges, Flanders","logo":"https://imgproxy.windy.com/_/icon/plain/current/1581419246/original.jpg","type":"webcam","url":"https://webcams.windy.com/webcams/public/embed/player/1581419246/day","source":"https://www.windy.com","source_name":"Windy"},{"iso":"BE","name":"Verviers: Laboru","description":"Verviers, Wallonia","logo":"https://imgproxy.windy.com/_/icon/plain/current/1585820141/original.jpg","type":"webcam","url":"https://webcams.windy.com/webcams/public/embed/player/1585820141/day","source":"https://www.windy.com","source_name":"Windy"},{"iso":"BE","name":"Bullingen › North","description":"Bullingen, Wallonia","logo":"https://imgproxy.windy.com/_/icon/plain/current/1587300182/original.jpg","type":"webcam","url":"https://webcams.windy.com/webcams/public/embed/player/1587300182/day","source":"https://www.windy.com","source_name":"Windy"},{"iso":"BE","name":"Knokke-Heist › North-west: RBSC Het Zoute","description":"Knokke-Heist, Flanders","logo":"https://imgproxy.windy.com/_/icon/plain/current/1591269789/original.jpg","type":"webcam","url":"https://webcams.windy.com/webcams/public/embed/player/1591269789/day","source":"https://www.windy.com","source_name":"Windy"},{"iso":"BE","name":"Beerse › North","description":"Beerse, Flanders","logo":"https://imgproxy.windy.com/_/icon/plain/current/1591992330/original.jpg","type":"webcam","url":"https://webcams.windy.com/webcams/public/embed/player/1591992330/day","source":"https://www.windy.com","source_name":"Windy"},{"iso":"BE","name":"Maasmechelen: St. Barbarakirche","description":"Maasmechelen, Flanders","logo":"https://imgproxy.windy.com/_/icon/plain/current/1594856891/original.jpg","type":"webcam","url":"https://webcams.windy.com/webcams/public/embed/player/1594856891/live","source":"https://www.windy.com","source_name":"Windy"},{"iso":"BE","name":"Maasmechelen: St. Barbarakirche","description":"Maasmechelen, Flanders","logo":"https://imgproxy.windy.com/_/icon/plain/current/1594856896/original.jpg","type":"webcam","url":"https://webcams.windy.com/webcams/public/embed/player/1594856896/live","source":"https://www.windy.com","source_name":"Windy"},{"iso":"BE","name":"Maasmechelen: St. Barbarakirche","description":"Maasmechelen, Flanders","logo":"https://imgproxy.windy.com/_/icon/plain/current/1594856902/original.jpg","type":"webcam","url":"https://webcams.windy.com/webcams/public/embed/player/1594856902/live","source":"https://www.windy.com","source_name":"Windy"},{"iso":"BE","name":"Maasmechelen: St. Barbarakirche","description":"Maasmechelen, Flanders","logo":"https://imgproxy.windy.com/_/icon/plain/current/1595288872/original.jpg","type":"webcam","url":"https://webcams.windy.com/webcams/public/embed/player/1595288872/live","source":"https://www.windy.com","source_name":"Windy"},{"iso":"BE","name":"Maasmechelen: St. Barbarakirche","description":"Maasmechelen, Flanders","logo":"https://imgproxy.windy.com/_/icon/plain/current/1595461683/original.jpg","type":"webcam","url":"https://webcams.windy.com/webcams/public/embed/player/1595461683/live","source":"https://www.windy.com","source_name":"Windy"},{"iso":"BE","name":"Maasmechelen: St. Barbarakirche","description":"Maasmechelen, Flanders","logo":"https://imgproxy.windy.com/_/icon/plain/current/1595461688/original.jpg","type":"webcam","url":"https://webcams.windy.com/webcams/public/embed/player/1595461688/live","source":"https://www.windy.com","source_name":"Windy"},{"iso":"BE","name":"Merksplas › North","description":"Merksplas, Flanders","logo":"https://imgproxy.windy.com/_/icon/plain/current/1597053241/original.jpg","type":"webcam","url":"https://webcams.windy.com/webcams/public/embed/player/1597053241/day","source":"https://www.windy.com","source_name":"Windy"},{"iso":"BE","name":"Houyet › North","description":"Houyet, Wallonia","logo":"https://imgproxy.windy.com/_/icon/plain/current/1597263050/original.jpg","type":"webcam","url":"https://webcams.windy.com/webcams/public/embed/player/1597263050/day","source":"https://www.windy.com","source_name":"Windy"},{"iso":"BE","name":"Harelbeke › North","description":"Harelbeke, Flanders","logo":"https://imgproxy.windy.com/_/icon/plain/current/1601628310/original.jpg","type":"webcam","url":"https://webcams.windy.com/webcams/public/embed/player/1601628310/day","source":"https://www.windy.com","source_name":"Windy"},{"iso":"BE","name":"De Haan › North-west","description":"De Haan, Flanders","logo":"https://imgproxy.windy.com/_/icon/plain/current/1601635690/original.jpg","type":"webcam","url":"https://webcams.windy.com/webcams/public/embed/player/1601635690/live","source":"https://www.windy.com","source_name":"Windy"},{"iso":"BE","name":"Wortegem-Petegem","description":"Wortegem-Petegem, Flanders","logo":"https://imgproxy.windy.com/_/icon/plain/current/1609080005/original.jpg","type":"webcam","url":"https://webcams.windy.com/webcams/public/embed/player/1609080005/day","source":"https://www.windy.com","source_name":"Windy"},{"iso":"BE","name":"Beersel › West","description":"Beersel, Flanders","logo":"https://imgproxy.windy.com/_/icon/plain/current/1609417481/original.jpg","type":"webcam","url":"https://webcams.windy.com/webcams/public/embed/player/1609417481/day","source":"https://www.windy.com","source_name":"Windy"},{"iso":"BE","name":"Libramont-Chevigny","description":"Libramont-Chevigny, Wallonia","logo":"https://imgproxy.windy.com/_/icon/plain/current/1609714626/original.jpg","type":"webcam","url":"https://webcams.windy.com/webcams/public/embed/player/1609714626/day","source":"https://www.windy.com","source_name":"Windy"},{"iso":"BE","name":"Butgenbach › North: Stausee Bütgenbach","description":"Butgenbach, Wallonia","logo":"https://imgproxy.windy.com/_/icon/plain/current/1610903932/original.jpg","type":"webcam","url":"https://webcams.windy.com/webcams/public/embed/player/1610903932/day","source":"https://www.windy.com","source_name":"Windy"},{"iso":"BE","name":"Sprimont: Dolembreux","description":"Sprimont, Wallonia","logo":"https://imgproxy.windy.com/_/icon/plain/current/1611232315/original.jpg","type":"webcam","url":"https://webcams.windy.com/webcams/public/embed/player/1611232315/day","source":"https://www.windy.com","source_name":"Windy"},{"iso":"BE","name":"Vielsalm › North-east: Baraque Fraiture","description":"Vielsalm, Wallonia","logo":"https://imgproxy.windy.com/_/icon/plain/current/1611844461/original.jpg","type":"webcam","url":"https://webcams.windy.com/webcams/public/embed/player/1611844461/day","source":"https://www.windy.com","source_name":"Windy"},{"iso":"BE","name":"Tournai: Mont-Saint-Aubert","description":"Tournai, Wallonia","logo":"https://imgproxy.windy.com/_/icon/plain/current/1611943176/original.jpg","type":"webcam","url":"https://webcams.windy.com/webcams/public/embed/player/1611943176/day","source":"https://www.windy.com","source_name":"Windy"},{"iso":"BE","name":"Blankenberge: O'Neill Beach Club - Strand Blankenberge pier","description":"Blankenberge, Flanders","logo":"https://imgproxy.windy.com/_/icon/plain/current/1617377416/original.jpg","type":"webcam","url":"https://webcams.windy.com/webcams/public/embed/player/1617377416/live","source":"https://www.windy.com","source_name":"Windy"},{"iso":"BE","name":"Hoegaarden","description":"Hoegaarden, Flanders","logo":"https://imgproxy.windy.com/_/icon/plain/current/1620642193/original.jpg","type":"webcam","url":"https://webcams.windy.com/webcams/public/embed/player/1620642193/day","source":"https://www.windy.com","source_name":"Windy"},{"iso":"BE","name":"Courcelles › South-east","description":"Courcelles, Wallonia","logo":"https://imgproxy.windy.com/_/icon/plain/current/1621009319/original.jpg","type":"webcam","url":"https://webcams.windy.com/webcams/public/embed/player/1621009319/day","source":"https://www.windy.com","source_name":"Windy"},{"iso":"BE","name":"Floreffe","description":"Floreffe, Wallonia","logo":"https://imgproxy.windy.com/_/icon/plain/current/1622290661/original.jpg","type":"webcam","url":"https://webcams.windy.com/webcams/public/embed/player/1622290661/day","source":"https://www.windy.com","source_name":"Windy"},{"iso":"BE","name":"Melle › North","description":"Melle, Flanders","logo":"https://imgproxy.windy.com/_/icon/plain/current/1622361625/original.jpg","type":"webcam","url":"https://webcams.windy.com/webcams/public/embed/player/1622361625/day","source":"https://www.windy.com","source_name":"Windy"},{"iso":"BE","name":"Antwerp › North","description":"Antwerp, Flanders","logo":"https://imgproxy.windy.com/_/icon/plain/current/1623586249/original.jpg","type":"webcam","url":"https://webcams.windy.com/webcams/public/embed/player/1623586249/day","source":"https://www.windy.com","source_name":"Windy"},{"iso":"BE","name":"Antwerp › North-east","description":"Antwerp, Flanders","logo":"https://imgproxy.windy.com/_/icon/plain/current/1623586256/original.jpg","type":"webcam","url":"https://webcams.windy.com/webcams/public/embed/player/1623586256/day","source":"https://www.windy.com","source_name":"Windy"},{"iso":"BE","name":"Antwerp › South-east","description":"Antwerp, Flanders","logo":"https://imgproxy.windy.com/_/icon/plain/current/1623586258/original.jpg","type":"webcam","url":"https://webcams.windy.com/webcams/public/embed/player/1623586258/day","source":"https://www.windy.com","source_name":"Windy"},{"iso":"BE","name":"Antwerp › South-west","description":"Antwerp, Flanders","logo":"https://imgproxy.windy.com/_/icon/plain/current/1623586260/original.jpg","type":"webcam","url":"https://webcams.windy.com/webcams/public/embed/player/1623586260/day","source":"https://www.windy.com","source_name":"Windy"},{"iso":"BE","name":"Antwerp › North-west","description":"Antwerp, Flanders","logo":"https://imgproxy.windy.com/_/icon/plain/current/1623586265/original.jpg","type":"webcam","url":"https://webcams.windy.com/webcams/public/embed/player/1623586265/day","source":"https://www.windy.com","source_name":"Windy"},{"iso":"BE","name":"Couvin","description":"Couvin, Wallonia","logo":"https://imgproxy.windy.com/_/icon/plain/current/1626292256/original.jpg","type":"webcam","url":"https://webcams.windy.com/webcams/public/embed/player/1626292256/day","source":"https://www.windy.com","source_name":"Windy"},{"iso":"BE","name":"Bredene","description":"Bredene, Flanders","logo":"https://imgproxy.windy.com/_/icon/plain/current/1626382629/original.jpg","type":"webcam","url":"https://webcams.windy.com/webcams/public/embed/player/1626382629/day","source":"https://www.windy.com","source_name":"Windy"},{"iso":"BE","name":"Koksijde","description":"Koksijde, Flanders","logo":"https://imgproxy.windy.com/_/icon/plain/current/1631432457/original.jpg","type":"webcam","url":"https://webcams.windy.com/webcams/public/embed/player/1631432457/day","source":"https://www.windy.com","source_name":"Windy"},{"iso":"BE","name":"Nieuwpoort","description":"Nieuwpoort, Flanders","logo":"https://imgproxy.windy.com/_/icon/plain/current/1632980371/original.jpg","type":"webcam","url":"https://webcams.windy.com/webcams/public/embed/player/1632980371/live","source":"https://www.windy.com","source_name":"Windy"},{"iso":"BE","name":"Bullingen › North-east: WIRTZFELD Kirche","description":"Bullingen, Wallonia","logo":"https://imgproxy.windy.com/_/icon/plain/current/1638364048/original.jpg","type":"webcam","url":"https://webcams.windy.com/webcams/public/embed/player/1638364048/day","source":"https://www.windy.com","source_name":"Windy"},{"iso":"BE","name":"Waregem › West","description":"Waregem, Flanders","logo":"https://imgproxy.windy.com/_/icon/plain/current/1638787041/original.jpg","type":"webcam","url":"https://webcams.windy.com/webcams/public/embed/player/1638787041/live","source":"https://www.windy.com","source_name":"Windy"},{"iso":"BE","name":"Waremme › South-west","description":"Waremme, Wallonia","logo":"https://imgproxy.windy.com/_/icon/plain/current/1639698956/original.jpg","type":"webcam","url":"https://webcams.windy.com/webcams/public/embed/player/1639698956/day","source":"https://www.windy.com","source_name":"Windy"},{"iso":"BE","name":"Evergem › North-west","description":"Evergem, Flanders","logo":"https://imgproxy.windy.com/_/icon/plain/current/1642667140/original.jpg","type":"webcam","url":"https://webcams.windy.com/webcams/public/embed/player/1642667140/day","source":"https://www.windy.com","source_name":"Windy"},{"iso":"BE","name":"Antwerp: Statiekwartier: Cam gras","description":"Antwerp, Flanders","logo":"https://imgproxy.windy.com/_/icon/plain/current/1648483886/original.jpg","type":"webcam","url":"https://webcams.windy.com/webcams/public/embed/player/1648483886/day","source":"https://www.windy.com","source_name":"Windy"},{"iso":"BE","name":"Wevelgem","description":"Wevelgem, Flanders","logo":"https://imgproxy.windy.com/_/icon/plain/current/1649592911/original.jpg","type":"webcam","url":"https://webcams.windy.com/webcams/public/embed/player/1649592911/day","source":"https://www.windy.com","source_name":"Windy"},{"iso":"BE","name":"Wevelgem › North-west: Moorsele Airfield","description":"Wevelgem, Flanders","logo":"https://imgproxy.windy.com/_/icon/plain/current/1649963539/original.jpg","type":"webcam","url":"https://webcams.windy.com/webcams/public/embed/player/1649963539/live","source":"https://www.windy.com","source_name":"Windy"},{"iso":"BE","name":"Ostend: Surfclub Inside Outside","description":"Ostend, Flanders","logo":"https://imgproxy.windy.com/_/icon/plain/current/1652858443/original.jpg","type":"webcam","url":"https://webcams.windy.com/webcams/public/embed/player/1652858443/live","source":"https://www.windy.com","source_name":"Windy"},{"iso":"BE","name":"Trois-Ponts","description":"Trois-Ponts, Wallonia","logo":"https://imgproxy.windy.com/_/icon/plain/current/1665441532/original.jpg","type":"webcam","url":"https://webcams.windy.com/webcams/public/embed/player/1665441532/day","source":"https://www.windy.com","source_name":"Windy"},{"iso":"BE","name":"Schaerbeek - Schaarbeek › North-west","description":"Schaerbeek - Schaarbeek, Brussels-Capital","logo":"https://imgproxy.windy.com/_/icon/plain/current/1667999005/original.jpg","type":"webcam","url":"https://webcams.windy.com/webcams/public/embed/player/1667999005/day","source":"https://www.windy.com","source_name":"Windy"},{"iso":"BE","name":"Bullingen › South","description":"Bullingen, Wallonia","logo":"https://imgproxy.windy.com/_/icon/plain/current/1670859703/original.jpg","type":"webcam","url":"https://webcams.windy.com/webcams/public/embed/player/1670859703/day","source":"https://www.windy.com","source_name":"Windy"},{"iso":"BE","name":"Waimes › South","description":"Waimes, Wallonia","logo":"https://imgproxy.windy.com/_/icon/plain/current/1671109618/original.jpg","type":"webcam","url":"https://webcams.windy.com/webcams/public/embed/player/1671109618/day","source":"https://www.windy.com","source_name":"Windy"},{"iso":"BE","name":"Neufchateau","description":"Neufchateau, Wallonia","logo":"https://imgproxy.windy.com/_/icon/plain/current/1671216228/original.jpg","type":"webcam","url":"https://webcams.windy.com/webcams/public/embed/player/1671216228/day","source":"https://www.windy.com","source_name":"Windy"},{"iso":"BE","name":"Yvoir › North-west","description":"Yvoir, Wallonia","logo":"https://imgproxy.windy.com/_/icon/plain/current/1677849044/original.jpg","type":"webcam","url":"https://webcams.windy.com/webcams/public/embed/player/1677849044/day","source":"https://www.windy.com","source_name":"Windy"},{"iso":"BE","name":"Harelbeke","description":"Harelbeke, Flanders","logo":"https://imgproxy.windy.com/_/icon/plain/current/1682236026/original.jpg","type":"webcam","url":"https://webcams.windy.com/webcams/public/embed/player/1682236026/day","source":"https://www.windy.com","source_name":"Windy"},{"iso":"BE","name":"Tienen › North-west","description":"Tienen, Flanders","logo":"https://imgproxy.windy.com/_/icon/plain/current/1690634726/original.jpg","type":"webcam","url":"https://webcams.windy.com/webcams/public/embed/player/1690634726/day","source":"https://www.windy.com","source_name":"Windy"},{"iso":"BE","name":"Bullingen","description":"Bullingen, Wallonia","logo":"https://imgproxy.windy.com/_/icon/plain/current/1704709645/original.jpg","type":"webcam","url":"https://webcams.windy.com/webcams/public/embed/player/1704709645/day","source":"https://www.windy.com","source_name":"Windy"},{"iso":"BE","name":"Dilsen-Stokkem: Stokkem: Dilsen - Meeswjk - Visitor Center De Wissen","description":"Dilsen-Stokkem, Flanders","logo":"https://imgproxy.windy.com/_/icon/plain/current/1719013929/original.jpg","type":"webcam","url":"https://webcams.windy.com/webcams/public/embed/player/1719013929/live","source":"https://www.windy.com","source_name":"Windy"},{"iso":"BE","name":"Kortenaken","description":"Kortenaken, Flanders","logo":"https://imgproxy.windy.com/_/icon/plain/current/1721477382/original.jpg","type":"webcam","url":"https://webcams.windy.com/webcams/public/embed/player/1721477382/day","source":"https://www.windy.com","source_name":"Windy"},{"iso":"BE","name":"Vise","description":"Vise, Wallonia","logo":"https://imgproxy.windy.com/_/icon/plain/current/1731331608/original.jpg","type":"webcam","url":"https://webcams.windy.com/webcams/public/embed/player/1731331608/day","source":"https://www.windy.com","source_name":"Windy"},{"iso":"BE","name":"Sprimont","description":"Sprimont, Wallonia","logo":"https://imgproxy.windy.com/_/icon/plain/current/1732045700/original.jpg","type":"webcam","url":"https://webcams.windy.com/webcams/public/embed/player/1732045700/day","source":"https://www.windy.com","source_name":"Windy"},{"iso":"BE","name":"City of Brussels","description":"City of Brussels, Brussels-Capital","logo":"https://imgproxy.windy.com/_/icon/plain/current/1736585384/original.jpg","type":"webcam","url":"https://webcams.windy.com/webcams/public/embed/player/1736585384/day","source":"https://www.windy.com","source_name":"Windy"},{"iso":"BE","name":"Sint-Katelijne-Waver › South","description":"Sint-Katelijne-Waver, Flanders","logo":"https://imgproxy.windy.com/_/icon/plain/current/1746372324/original.jpg","type":"webcam","url":"https://webcams.windy.com/webcams/public/embed/player/1746372324/day","source":"https://www.windy.com","source_name":"Windy"},{"iso":"BE","name":"City of Brussels: Grand Place","description":"City of Brussels, Brussels-Capital","logo":"https://imgproxy.windy.com/_/icon/plain/current/1761136786/original.jpg","type":"webcam","url":"https://webcams.windy.com/webcams/public/embed/player/1761136786/day","source":"https://www.windy.com","source_name":"Windy"},{"iso":"BE","name":"Spa › South-west: Domain of Bérinzenne","description":"Spa, Wallonia","logo":"https://imgproxy.windy.com/_/icon/plain/current/1793896777/original.jpg","type":"webcam","url":"https://webcams.windy.com/webcams/public/embed/player/1793896777/day","source":"https://www.windy.com","source_name":"Windy"},{"iso":"BE","name":"Saint Vith › South","description":"Saint Vith, Wallonia","logo":"https://imgproxy.windy.com/_/icon/plain/current/1793899009/original.jpg","type":"webcam","url":"https://webcams.windy.com/webcams/public/embed/player/1793899009/day","source":"https://www.windy.com","source_name":"Windy"},{"iso":"BE","name":"Chiny › South-east: Moyen","description":"Chiny, Wallonia","logo":"https://imgproxy.windy.com/_/icon/plain/current/1793899010/original.jpg","type":"webcam","url":"https://webcams.windy.com/webcams/public/embed/player/1793899010/day","source":"https://www.windy.com","source_name":"Windy"},{"iso":"BE","name":"Zottegem: Erwetegem","description":"Zottegem, Flanders","logo":"https://imgproxy.windy.com/_/icon/plain/current/1793899013/original.jpg","type":"webcam","url":"https://webcams.windy.com/webcams/public/embed/player/1793899013/day","source":"https://www.windy.com","source_name":"Windy"},{"iso":"BE","name":"Avelgem › South-east","description":"Avelgem, Flanders","logo":"https://imgproxy.windy.com/_/icon/plain/current/1793899016/original.jpg","type":"webcam","url":"https://webcams.windy.com/webcams/public/embed/player/1793899016/day","source":"https://www.windy.com","source_name":"Windy"},{"iso":"BE","name":"Ostend › North-west: Ostend Sailing Private Club, Phare East & The Outsider Oostende","description":"Ostend, Flanders","logo":"https://imgproxy.windy.com/_/icon/plain/current/1793899017/original.jpg","type":"webcam","url":"https://webcams.windy.com/webcams/public/embed/player/1793899017/day","source":"https://www.windy.com","source_name":"Windy"},{"iso":"BE","name":"Walhain › North-east","description":"Walhain, Wallonia","logo":"https://imgproxy.windy.com/_/icon/plain/current/1793899019/original.jpg","type":"webcam","url":"https://webcams.windy.com/webcams/public/embed/player/1793899019/day","source":"https://www.windy.com","source_name":"Windy"},{"iso":"BE","name":"Namur › South-east: Jambes","description":"Namur, Wallonia","logo":"https://imgproxy.windy.com/_/icon/plain/current/1793899020/original.jpg","type":"webcam","url":"https://webcams.windy.com/webcams/public/embed/player/1793899020/day","source":"https://www.windy.com","source_name":"Windy"},{"iso":"BE","name":"La Roche-en-Ardenne › South: Beausaint","description":"La Roche-en-Ardenne, Wallonia","logo":"https://imgproxy.windy.com/_/icon/plain/current/1793899022/original.jpg","type":"webcam","url":"https://webcams.windy.com/webcams/public/embed/player/1793899022/day","source":"https://www.windy.com","source_name":"Windy"},{"iso":"BE","name":"Waimes: Sourbrodt","description":"Waimes, Wallonia","logo":"https://imgproxy.windy.com/_/icon/plain/current/1793899024/original.jpg","type":"webcam","url":"https://webcams.windy.com/webcams/public/embed/player/1793899024/day","source":"https://www.windy.com","source_name":"Windy"}]}
